{
	"animations": [
		{
			"loop": false,
			"offsets": [
				-1,
				0
			],
			"anim": "death",
			"fps": 24,
			"name": "DONALD DEATH",
			"indices": [
				1,
				2,
				3,
				4,
				5,
				6,
				7,
				8,
				9,
				10,
				11,
				12,
				13,
				14,
				15
			]
		},
		{
			"loop": false,
			"offsets": [
				-85,
				-675
			],
			"anim": "idle",
			"fps": 24,
			"name": "DONALD DEATH IDLE",
			"indices": []
		},
		{
			"loop": false,
			"offsets": [
				570,
				846
			],
			"anim": "appear",
			"fps": 24,
			"name": "DUCK APAR",
			"indices": []
		}
	],
	"no_antialiasing": false,
	"image": "characters/accelerant/DONALD_EXTRA_ANIMATIONS",
	"position": [
		285,
		-684
	],
	"healthicon": "gf",
	"flip_x": false,
	"healthbar_colors": [
		165,
		0,
		77
	],
	"camera_position": [
		0,
		0
	],
	"sing_duration": 4,
	"scale": 1
}