{
	"animations": [
		{
			"offsets": [
				-5,
				2
			],
			"loop": false,
			"fps": 24,
			"anim": "idle",
			"indices": [],
			"name": "LEAKER 2 IDLE"
		},
		{
			"offsets": [
				-31,
				-7
			],
			"loop": false,
			"fps": 24,
			"anim": "singDOWN",
			"indices": [],
			"name": "leaker 2 DOWN0"
		},
		{
			"offsets": [
				81,
				247
			],
			"loop": false,
			"fps": 24,
			"anim": "singUP",
			"indices": [],
			"name": "LEAKER 2 UP"
		},
		{
			"loop": false,
			"offsets": [
				299,
				3
			],
			"anim": "singLEFT",
			"fps": 24,
			"name": "LEAKER 2 LEFT",
			"indices": []
		},
		{
			"loop": false,
			"offsets": [
				-110,
				-44
			],
			"anim": "singRIGHT",
			"fps": 24,
			"name": "LEAKER 2 RIGHT",
			"indices": []
		}
	],
	"no_antialiasing": false,
	"image": "characters/mwehehehe/LEAKER_2",
	"position": [
		10,
		120
	],
	"healthicon": "bf",
	"flip_x": false,
	"healthbar_colors": [
		49,
		176,
		209
	],
	"camera_position": [
		0,
		0
	],
	"sing_duration": 5.4,
	"scale": 1
}